{
  "type": "FeatureCollection",
  "name": "SELECT",
  "features": [
    {
      "type": "Feature",
      "properties": {
        "RMC": "123_2328",
        "site": 123,
        "drive": 2328,
        "sol": 4959,
        "easting": 8143458.688,
        "northing": -285698.77,
        "elev_geoid": -3531.088,
        "lon": 137.3850737,
        "lat": -4.81991106,
        "roll": -4.1,
        "pitch": 5.63,
        "yaw": 112.55,
        "yaw_rad": 2.01244,
        "tilt": 6.96,
        "dist_m": 58.45,
        "dist_total_m": 37874.92,
        "dist_km": 37.56,
        "dist_mi": 23.34,
        "drive_type": "final"
      },
      "geometry": {
        "type": "Point",
        "coordinates": [
          137.3850737,
          -4.81991106,
          -3531.088
        ]
      }
    }
  ]
}