{
  "type": "FeatureCollection",
  "name": "SELECT",
  "features": [
    {
      "type": "Feature",
      "properties": {
        "RMC": "123_1890",
        "site": 123,
        "drive": 1890,
        "sol": 4957,
        "easting": 8143441.019,
        "northing": -285752.125,
        "elev_geoid": -3526.324,
        "lon": 137.3847756,
        "lat": -4.82081119,
        "roll": -4.1,
        "pitch": 5.63,
        "yaw": 112.55,
        "yaw_rad": 0.21508,
        "tilt": 6.96,
        "dist_m": 48.93,
        "dist_total_m": 37816.47,
        "dist_km": 37.5,
        "dist_mi": 23.3,
        "drive_type": "final"
      },
      "geometry": {
        "type": "Point",
        "coordinates": [
          137.3847756,
          -4.82081119,
          -3526.324
        ]
      }
    }
  ]
}