{
  "type": "FeatureCollection",
  "name": "MSL_waypoints_current_sol4953",
  "features": [
    {
      "type": "Feature",
      "properties": {
        "RMC": "123_1344",
        "site": 123,
        "drive": 1344,
        "sol": 4953,
        "easting": 8143407.046,
        "northing": -285793.83,
        "elev_geoid": -3521.673,
        "lon": 137.38420247,
        "lat": -4.82151478,
        "roll": -4.1,
        "pitch": 5.63,
        "yaw": 112.55,
        "yaw_rad": 1.9644,
        "tilt": 6.96,
        "dist_m": 25.14,
        "dist_total_m": 37740.55,
        "dist_km": 37.43,
        "dist_mi": 23.25,
        "drive_type": "final"
      },
      "geometry": {
        "type": "Point",
        "coordinates": [
          137.38420247,
          -4.82151478,
          -3521.673
        ]
      }
    }
  ]
}