{
  "type": "FeatureCollection",
  "name": "MSL_waypoints_current_sol4939",
  "features": [
    {
      "type": "Feature",
      "properties": {
        "RMC": "123_0",
        "site": 123,
        "drive": 0,
        "sol": 4939,
        "easting": 8143347.327,
        "northing": -285655.253,
        "elev_geoid": -3539.047,
        "lon": 137.38319498,
        "lat": -4.8191769,
        "roll": 5.49,
        "pitch": 6.83,
        "yaw": 177.84,
        "yaw_rad": 3.10392,
        "tilt": 8.76,
        "dist_m": 50.67,
        "dist_total_m": 37567.83,
        "dist_km": 37.26,
        "dist_mi": 23.15,
        "drive_type": "final"
      },
      "geometry": {
        "type": "Point",
        "coordinates": [
          137.38319498,
          -4.8191769,
          -3539.047
        ]
      }
    }
  ]
}